files_interaction.py
files_interaction-1.0.3.dist-info/METADATA
files_interaction-1.0.3.dist-info/WHEEL
files_interaction-1.0.3.dist-info/RECORD
