Metadata-Version: 2.1
Name: files-interaction
Version: 1.0.3
Summary: Makes file interaction easier
Author: LooNuH
Requires-Python: >=3.10,<4.0
Classifier: Programming Language :: Python :: 3
Classifier: Programming Language :: Python :: 3.10
Classifier: Programming Language :: Python :: 3.11
Classifier: Programming Language :: Python :: 3.12
